{"config":{"output_file":null,"full_docs":false,"pub_only":true,"reachable_only":true,"distro_crate":false,"signatures":false,"borrow_data":false},"version":"0.18.1","compilation":{"directory":[47,104,111,109,101,47,97,114,103,111,115,47,84,104,101,115,101,117,115,47,108,105,98,115,47,109,97,116,114,105,120,109,117,108,116,105,112,108,121],"program":"/home/argos/.rustup/toolchains/nightly-2018-11-21-x86_64-unknown-linux-gnu/bin/rls","arguments":["--crate-name","build_script_build","build.rs","--color","never","--crate-type","bin","--emit=dep-info,link","-C","debuginfo=2","-C","metadata=9ab2a54a4cc7d6fd","-C","extra-filename=-9ab2a54a4cc7d6fd","--out-dir","/home/argos/Theseus/libs/matrixmultiply/target/rls/debug/build/matrixmultiply-9ab2a54a4cc7d6fd","-C","incremental=/home/argos/Theseus/libs/matrixmultiply/target/rls/debug/incremental","-L","dependency=/home/argos/Theseus/libs/matrixmultiply/target/rls/debug/deps","--error-format=json","--sysroot","/home/argos/.rustup/toolchains/nightly-2018-11-21-x86_64-unknown-linux-gnu"],"output":[47,104,111,109,101,47,97,114,103,111,115,47,84,104,101,115,101,117,115,47,108,105,98,115,47,109,97,116,114,105,120,109,117,108,116,105,112,108,121,47,116,97,114,103,101,116,47,114,108,115,47,100,101,98,117,103,47,98,117,105,108,100,47,109,97,116,114,105,120,109,117,108,116,105,112,108,121,45,57,97,98,50,97,53,52,97,52,99,99,55,100,54,102,100,47,98,117,105,108,100,95,115,99,114,105,112,116,95,98,117,105,108,100,45,57,97,98,50,97,53,52,97,52,99,99,55,100,54,102,100]},"prelude":{"crate_id":{"name":"build_script_build","disambiguator":[4332893185742794742,10400828519163529663]},"crate_root":"","external_crates":[{"file_name":"/home/argos/Theseus/libs/matrixmultiply/build.rs","num":1,"id":{"name":"std","disambiguator":[15459506237779174099,3368126863962929726]}},{"file_name":"/home/argos/Theseus/libs/matrixmultiply/build.rs","num":2,"id":{"name":"core","disambiguator":[18375901432589899259,12339129121913221916]}},{"file_name":"/home/argos/Theseus/libs/matrixmultiply/build.rs","num":3,"id":{"name":"compiler_builtins","disambiguator":[834164109761435412,10424036223137657165]}},{"file_name":"/home/argos/Theseus/libs/matrixmultiply/build.rs","num":4,"id":{"name":"alloc","disambiguator":[4472283272264780726,13198020728354615618]}},{"file_name":"/home/argos/Theseus/libs/matrixmultiply/build.rs","num":5,"id":{"name":"libc","disambiguator":[18075373443934541300,5321748813942924084]}},{"file_name":"/home/argos/Theseus/libs/matrixmultiply/build.rs","num":6,"id":{"name":"unwind","disambiguator":[14495180130903830410,560551018696677743]}},{"file_name":"/home/argos/Theseus/libs/matrixmultiply/build.rs","num":7,"id":{"name":"panic_unwind","disambiguator":[12376093437817091712,16965889865237553759]}}],"span":{"file_name":[98,117,105,108,100,46,114,115],"byte_start":1,"byte_end":293,"line_start":2,"line_end":14,"column_start":1,"column_end":2}},"imports":[],"defs":[{"kind":"Mod","id":{"krate":0,"index":0},"span":{"file_name":[98,117,105,108,100,46,114,115],"byte_start":1,"byte_end":293,"line_start":2,"line_end":14,"column_start":1,"column_end":2},"name":"","qualname":"::","value":"build.rs","parent":null,"children":[{"krate":0,"index":2},{"krate":0,"index":4},{"krate":0,"index":6},{"krate":0,"index":8}],"decl_id":null,"docs":"\n","sig":null,"attributes":[]}],"impls":[],"refs":[],"macro_refs":[],"relations":[]}